flask_management_endpoints/__init__.py
flask_management_endpoints/blueprint.py
flask_management_endpoints/ext.py
flask_management_endpoints/info.py
flask_management_endpoints/log.py
flask_management_endpoints/test_blueprint.py
flask_management_endpoints/test_cluster_info.py
flask_management_endpoints-1.1.0.dist-info/LICENSE
flask_management_endpoints-1.1.0.dist-info/METADATA
flask_management_endpoints-1.1.0.dist-info/WHEEL
flask_management_endpoints-1.1.0.dist-info/top_level.txt
flask_management_endpoints-1.1.0.dist-info/RECORD
