Metadata-Version: 2.1
Name: flask-management-endpoints
Version: 1.1.0
Summary: A module for adding Spring Actuator style health endpoints to your Flask application
Home-page: https://github.com/dekobon/flask-management-endpoints
Author: Elijah Zupancic
Author-email: elijah@zupancic.name
License: UNKNOWN
Project-URL: Bug Tracker, https://github.com/dekobon/flask-management-endpoints/issues
Platform: UNKNOWN
Classifier: Programming Language :: Python :: 3
Classifier: License :: OSI Approved :: BSD License
Classifier: Operating System :: OS Independent
Requires-Python: >=3.6
License-File: LICENSE
